{
    "client": "Thunder Client",
    "collectionName": "TrybeCar",
    "dateExported": "2023-05-17T22:21:16.755Z",
    "version": "1.1",
    "folders": [
        {
            "_id": "ad7b5e29-9911-44a1-931c-66d12753b39e",
            "name": "Driver",
            "containerId": "",
            "created": "2023-05-16T12:17:10.940Z",
            "sortNum": 5000
        },
        {
            "_id": "cc945e32-c771-4838-9c1a-a15de04b0e03",
            "name": "Passengers",
            "containerId": "",
            "created": "2023-05-16T12:17:03.343Z",
            "sortNum": 10000
        },
        {
            "_id": "ffc9c0e2-dc66-47d4-a731-de6ea7fe8402",
            "name": "Cars",
            "containerId": "",
            "created": "2023-05-16T12:17:26.064Z",
            "sortNum": 40000
        }
    ],
    "requests": [
        {
            "_id": "ef683bb3-e17c-451a-933e-9af0d0bd59d7",
            "colId": "1d0d0ec6-f34f-45c8-a886-934800de85ff",
            "containerId": "cc945e32-c771-4838-9c1a-a15de04b0e03",
            "name": "Criar Viagem (Passageiro)",
            "url": "http://localhost:3001/passengers/3/request/travel",
            "method": "POST",
            "sortNum": 10000,
            "created": "2023-01-10T16:45:28.701Z",
            "modified": "2023-05-16T12:17:31.111Z",
            "headers": [],
            "params": [],
            "body": {
                "type": "json",
                "raw": "{\n  \"startingAddress\": \"Rua AAA\",\n  \"endingAddress\": \"Rua BBBB\",\n  \"waypoints\": [\n    {\n      \"address\": \"Ponto CCCC\",\n      \"stopOrder\": 1\n    },\n    {\n      \"address\": \"Ponto DDDD\",\n      \"stopOrder\": 2\n    },\n    {\n      \"address\": \"Ponto 3\",\n      \"stopOrder\": 3\n    }\n  ]\n}",
                "form": []
            },
            "tests": []
        },
        {
            "_id": "f7414088-28be-4f15-b9b9-36fc9126e293",
            "colId": "1d0d0ec6-f34f-45c8-a886-934800de85ff",
            "containerId": "ad7b5e29-9911-44a1-931c-66d12753b39e",
            "name": "Listar Viagens Abertas (Motorista)",
            "url": "http://localhost:3001/drivers/open/travels",
            "method": "GET",
            "sortNum": 10000,
            "created": "2023-01-10T16:45:28.702Z",
            "modified": "2023-05-16T12:17:34.310Z",
            "headers": [],
            "params": [],
            "tests": []
        },
        {
            "_id": "eefb59c8-5dc1-48f2-bfc6-f6fc1720d523",
            "colId": "1d0d0ec6-f34f-45c8-a886-934800de85ff",
            "containerId": "ffc9c0e2-dc66-47d4-a731-de6ea7fe8402",
            "name": "Cadastrar carro",
            "url": "http://localhost:3001/cars",
            "method": "POST",
            "sortNum": 10000,
            "created": "2023-01-10T16:45:28.707Z",
            "modified": "2023-05-17T14:56:18.689Z",
            "headers": [],
            "params": [],
            "body": {
                "type": "json",
                "raw": "{\n  \"model\": \"Ford Ka\",\n  \"color\": \"Amarelo\",\n  \"licensePlate\": \"ABC1D2E\",\n  \"driverId\": 1\n}",
                "form": []
            },
            "tests": []
        },
        {
            "_id": "cd31fa7a-ffcb-4b29-9d8b-5989ba2270b5",
            "colId": "1d0d0ec6-f34f-45c8-a886-934800de85ff",
            "containerId": "ad7b5e29-9911-44a1-931c-66d12753b39e",
            "name": "Iniciar Viagem (Motorista)",
            "url": "http://localhost:3001/drivers/1/travels/1/assign",
            "method": "PUT",
            "sortNum": 30000,
            "created": "2023-01-10T16:45:28.704Z",
            "modified": "2023-05-17T14:05:53.149Z",
            "headers": [],
            "params": [],
            "tests": []
        },
        {
            "_id": "9e4914c7-5280-4efb-8a5b-624a40ecec83",
            "colId": "1d0d0ec6-f34f-45c8-a886-934800de85ff",
            "containerId": "ad7b5e29-9911-44a1-931c-66d12753b39e",
            "name": "Finalizar Viagem (Motorista)",
            "url": "http://localhost:3001/drivers/1/travels/1/end",
            "method": "PUT",
            "sortNum": 40000,
            "created": "2023-01-10T16:45:28.705Z",
            "modified": "2023-05-16T12:17:40.797Z",
            "headers": [],
            "params": [],
            "tests": []
        },
        {
            "_id": "0201972e-9205-4ee5-87da-12a8aadf230f",
            "colId": "1d0d0ec6-f34f-45c8-a886-934800de85ff",
            "containerId": "ad7b5e29-9911-44a1-931c-66d12753b39e",
            "name": "Listar motoristas",
            "url": "http://localhost:3001/drivers",
            "method": "GET",
            "sortNum": 50000,
            "created": "2023-01-10T16:45:28.706Z",
            "modified": "2023-05-16T12:17:45.313Z",
            "headers": [],
            "params": [],
            "tests": []
        },
        {
            "_id": "7d61e0f6-7012-4b01-9db2-7e9f27e6f6fa",
            "colId": "1d0d0ec6-f34f-45c8-a886-934800de85ff",
            "containerId": "ad7b5e29-9911-44a1-931c-66d12753b39e",
            "name": "Criar motorista",
            "url": "http://localhost:3001/drivers",
            "method": "POST",
            "sortNum": 60000,
            "created": "2023-01-10T16:45:28.708Z",
            "modified": "2023-05-16T12:17:49.882Z",
            "headers": [],
            "params": [],
            "body": {
                "type": "json",
                "raw": "{\n  \"name\": \"Gus\",\n  \"carIds\": [\n    1,\n    2\n  ]\n}",
                "form": []
            },
            "tests": []
        },
        {
            "_id": "50aa10b8-0e61-4049-9256-898cf008473f",
            "colId": "1d0d0ec6-f34f-45c8-a886-934800de85ff",
            "containerId": "cc945e32-c771-4838-9c1a-a15de04b0e03",
            "name": "Listar Passageiros",
            "url": "http://localhost:3001/passengers",
            "method": "GET",
            "sortNum": 90000,
            "created": "2023-05-16T12:18:05.359Z",
            "modified": "2023-05-16T12:18:20.070Z",
            "headers": [],
            "params": [],
            "tests": []
        },
        {
            "_id": "7b65ee12-b442-4f4a-a531-44dc3b78b714",
            "colId": "1d0d0ec6-f34f-45c8-a886-934800de85ff",
            "containerId": "cc945e32-c771-4838-9c1a-a15de04b0e03",
            "name": "Listar Passageiro por Id",
            "url": "http://localhost:3001/passengers/100",
            "method": "GET",
            "sortNum": 100000,
            "created": "2023-05-16T12:22:40.696Z",
            "modified": "2023-05-16T12:23:09.455Z",
            "headers": [],
            "params": [],
            "tests": []
        }
    ]
}
